generate_routers/cli.py
generate_routers/generate_routers.py
generate_routers_fastapi_generator_jvngarcia-0.1.1.dist-info/METADATA
generate_routers_fastapi_generator_jvngarcia-0.1.1.dist-info/WHEEL
generate_routers_fastapi_generator_jvngarcia-0.1.1.dist-info/entry_points.txt
generate_routers_fastapi_generator_jvngarcia-0.1.1.dist-info/top_level.txt
generate_routers_fastapi_generator_jvngarcia-0.1.1.dist-info/RECORD
