Metadata-Version: 2.1
Name: generate-routers-fastapi-generator-jvngarcia
Version: 0.1.1
Summary: Sistema para crear rutas para proyecto de nuevo generador de código SQL: fastapi-generator 
Home-page: https://github.com/jvngarcia/generate-routers-fastapi-generator
Author: Ángel García
Author-email: angelgarciaweb@gmail.com
Project-URL: Bug Tracker, https://github.com/jvngarcia/generate-routers-fastapi-generator/issues
Classifier: Programming Language :: Python :: 3
Classifier: License :: OSI Approved :: MIT License
Classifier: Operating System :: OS Independent
Requires-Python: >=3.6
Requires-Dist: requests
